aichat/__init__.py
aichat/audio.py.wip
aichat/brain.py
aichat/compose.py
aichat/console.py
aichat/constants.py
aichat/context.py
aichat/manage.py
aichat/pattern.py
aichat/skeleton.py
aichat/voice.py
aichat/voice.py.wip
aichat/chatapp/__init__.py
aichat/chatapp/admin.py
aichat/chatapp/apps.py
aichat/chatapp/load.py
aichat/chatapp/models.py
aichat/chatapp/tests.py
aichat/chatapp/urls.py
aichat/chatapp/views.py
aichat/chatapp/data/bluetooth.csv
aichat/chatapp/data/callAgent.csv
aichat/chatapp/data/chloe.csv
aichat/chatapp/data/chloeSkills.csv
aichat/chatapp/data/commands.csv
aichat/chatapp/data/horizonFirstBoot.csv
aichat/chatapp/data/jokes.csv
aichat/chatapp/data/quotes.csv
aichat/chatapp/data/releaseNotes.csv
aichat/chatapp/data/riddles.csv
aichat/chatapp/data/tips.csv
aichat/chatapp/data/tutorial.csv
aichat/chatapp/migrations/0001_initial.py
aichat/chatapp/migrations/__init__.py
aichat/chatsite/__init__.py
aichat/chatsite/secret_create_superuser.py
aichat/chatsite/secret_settings.py
aichat/chatsite/settings.py
aichat/chatsite/urls.py
aichat/chatsite/wsgi.py
aichat/devops/compose.py
aichat/scripts/audio.py.wip
aichat/scripts/bot.py
aichat/scripts/circlevoice.py.wip
aichat/scripts/curate.sh
aichat/scripts/deepvoice.py.wip
aichat/website/manage.py
aichat/website/chatapp/__init__.py
aichat/website/chatapp/admin.py
aichat/website/chatapp/apps.py
aichat/website/chatapp/load.py
aichat/website/chatapp/models.py
aichat/website/chatapp/tests.py
aichat/website/chatapp/urls.py
aichat/website/chatapp/views.py
aichat/website/chatapp/data/bluetooth.csv
aichat/website/chatapp/data/callAgent.csv
aichat/website/chatapp/data/chloe.csv
aichat/website/chatapp/data/chloeSkills.csv
aichat/website/chatapp/data/commands.csv
aichat/website/chatapp/data/horizonFirstBoot.csv
aichat/website/chatapp/data/jokes.csv
aichat/website/chatapp/data/quotes.csv
aichat/website/chatapp/data/releaseNotes.csv
aichat-0.0.5.dist-info/METADATA
aichat-0.0.5.dist-info/RECORD
aichat-0.0.5.dist-info/WHEEL
aichat-0.0.5.dist-info/entry_points.txt
aichat-0.0.5.dist-info/top_level.txt
