Metadata-Version: 2.1
Name: aichat
Version: 0.0.5
Summary: A AI virtual assistant chatbot
Home-page: http://aichat.aira.io
Author: Aira
Author-email: github@totalgood.com
License: mit
Platform: any
Classifier: Development Status :: 4 - Beta
Classifier: Programming Language :: Python
Classifier: Programming Language :: Python :: 3.6
Classifier: Topic :: Communications :: Chat
Classifier: Natural Language :: English
Provides-Extra: generate
Provides-Extra: audio
Provides-Extra: django
Provides-Extra: all
Provides-Extra: voice
Requires-Dist: django
Requires-Dist: spacy
Requires-Dist: nltk
Requires-Dist: scipy
Requires-Dist: numpy
Requires-Dist: exrex
Requires-Dist: regex
Requires-Dist: pugnlp
Provides-Extra: all
Requires-Dist: aichat[generate]; extra == 'all'
Requires-Dist: aichat[voice]; extra == 'all'
Requires-Dist: aichat[django]; extra == 'all'
Provides-Extra: audio
Requires-Dist: scipy; extra == 'audio'
Requires-Dist: numpy; extra == 'audio'
Requires-Dist: pyaudio; extra == 'audio'
Provides-Extra: django
Requires-Dist: django; extra == 'django'
Provides-Extra: generate
Requires-Dist: exrex; extra == 'generate'
Provides-Extra: voice
Requires-Dist: aichat[audio]; extra == 'voice'
Requires-Dist: deepspeech; extra == 'voice'
Requires-Dist: SpeechRecognition; extra == 'voice'
Requires-Dist: pyttsx3; extra == 'voice'
